{
  "type": "Feature",
  "stac_version": "1.0.0",
  "id": "ib10000_9-NE",
  "properties": {
    "datetime": "2024-11-14T00:00:00Z"
  },
  "geometry": {
    "coordinates": [
      [
        [
          [
            113.97039575689122,
            22.354993472567198
          ],
          [
            113.97047546322779,
            22.300810320529795
          ],
          [
            113.89769102805566,
            22.300701426129386
          ],
          [
            113.89758320892302,
            22.35488428402966
          ],
          [
            113.97039575689122,
            22.354993472567198
          ]
        ]
      ]
    ],
    "type": "MultiPolygon"
  },
  "links": [
    {
      "rel": "root",
      "href": "../catalog.json",
      "type": "application/json"
    },
    {
      "rel": "parent",
      "href": "./ib10000.json",
      "type": "application/json"
    },
    {
      "rel": "collection",
      "href": "./ib10000.json",
      "type": "application/json"
    }
  ],
  "assets": {
    "TIFF": {
      "href": "https://open.hkmapservice.gov.hk/OpenData/directDownload?productName=iB10000&sheetName=T9-NE&productFormat=TIFF",
      "type": "image/tiff; application=geotiff"
    },
    "DWG": {
      "href": "https://open.hkmapservice.gov.hk/OpenData/directDownload?productName=iB10000&sheetName=T9-NE&productFormat=DWG",
      "type": "application/dwg"
    },
    "GML": {
      "href": "https://open.hkmapservice.gov.hk/OpenData/directDownload?productName=iB10000&sheetName=T9-NE&productFormat=GML",
      "type": "application/gml+xml"
    },
    "DGN": {
      "href": "https://open.hkmapservice.gov.hk/OpenData/directDownload?productName=iB10000&sheetName=T9-NE&productFormat=DGN",
      "type": "application/dgn"
    },
    "FGDB": {
      "href": "https://open.hkmapservice.gov.hk/OpenData/directDownload?productName=iB10000&sheetName=T9-NE&productFormat=FGDB",
      "type": "application/x-filegdb"
    }
  },
  "bbox": [
    113.89758320892302,
    22.300701426129386,
    113.97047546322779,
    22.354993472567198
  ],
  "stac_extensions": [],
  "collection": "ib10000"
}