{
  "type": "Feature",
  "stac_version": "1.0.0",
  "stac_extensions": [],
  "id": "15-NE-20A_cog_wgs84",
  "geometry": {
    "type": "Polygon",
    "coordinates": [
      [
        [
          114.24701254369408,
          22.208808406685915
        ],
        [
          114.25429043180922,
          22.208808406685915
        ],
        [
          114.25429043180922,
          22.214232040511995
        ],
        [
          114.24701254369408,
          22.214232040511995
        ],
        [
          114.24701254369408,
          22.208808406685915
        ]
      ]
    ]
  },
  "bbox": [
    114.24701254369408,
    22.208808406685915,
    114.25429043180922,
    22.214232040511995
  ],
  "properties": {
    "datetime": "2024-12-10T08:08:09.464708Z"
  },
  "links": [
    {
      "rel": "root",
      "href": "/content/ib1000_stac/catalog.json",
      "type": "application/json"
    },
    {
      "rel": "parent",
      "href": "/content/ib1000_stac/ib1000/collection.json",
      "type": "application/json",
      "title": "IB1000 COG Collection"
    },
    {
      "rel": "collection",
      "href": "/content/ib1000_stac/ib1000/collection.json",
      "type": "application/json",
      "title": "IB1000 COG Collection"
    },
    {
      "rel": "self",
      "href": "/content/ib1000_stac/items/15-NE-20A_cog_wgs84.json",
      "type": "application/json"
    }
  ],
  "assets": {
    "cog": {
      "href": "https://github.com/Anna-leungtn/STAC_CSDI/raw/refs/heads/main/ib1000-wgs/15-NE-20A_cog_wgs84.tif",
      "type": "image/tiff; application=geotiff; profile=cloud-optimized",
      "roles": [
        "data"
      ]
    }
  },
  "collection": "ib1000"
}