{
  "type": "Feature",
  "stac_version": "1.0.0",
  "stac_extensions": [],
  "id": "2-SE-15A_cog_wgs84",
  "geometry": {
    "type": "Polygon",
    "coordinates": [
      [
        [
          114.10138292555416,
          22.490563117428213
        ],
        [
          114.1086754393203,
          22.490563117428213
        ],
        [
          114.1086754393203,
          22.49598606382018
        ],
        [
          114.10138292555416,
          22.49598606382018
        ],
        [
          114.10138292555416,
          22.490563117428213
        ]
      ]
    ]
  },
  "bbox": [
    114.10138292555416,
    22.490563117428213,
    114.1086754393203,
    22.49598606382018
  ],
  "properties": {
    "datetime": "2024-12-10T08:08:39.779154Z"
  },
  "links": [
    {
      "rel": "root",
      "href": "/content/ib1000_stac/catalog.json",
      "type": "application/json"
    },
    {
      "rel": "parent",
      "href": "/content/ib1000_stac/ib1000/collection.json",
      "type": "application/json",
      "title": "IB1000 COG Collection"
    },
    {
      "rel": "collection",
      "href": "/content/ib1000_stac/ib1000/collection.json",
      "type": "application/json",
      "title": "IB1000 COG Collection"
    },
    {
      "rel": "self",
      "href": "/content/ib1000_stac/items/2-SE-15A_cog_wgs84.json",
      "type": "application/json"
    }
  ],
  "assets": {
    "cog": {
      "href": "https://github.com/Anna-leungtn/STAC_CSDI/raw/refs/heads/main/ib1000-wgs/2-SE-15A_cog_wgs84.tif",
      "type": "image/tiff; application=geotiff; profile=cloud-optimized",
      "roles": [
        "data"
      ]
    }
  },
  "collection": "ib1000"
}